lmdbdict/__init__.py
lmdbdict/lmdbdict.py
lmdbdict/methods.py
lmdbdict/utils.py
lmdbdict-0.2.2.dist-info/LICENSE
lmdbdict-0.2.2.dist-info/METADATA
lmdbdict-0.2.2.dist-info/WHEEL
lmdbdict-0.2.2.dist-info/top_level.txt
lmdbdict-0.2.2.dist-info/RECORD
