Metadata-Version: 2.1
Name: lmdbdict
Version: 0.2.2
Summary: UNKNOWN
Home-page: UNKNOWN
Author: Ruotian Luo
Author-email: rluo@ttic.edu
License: UNKNOWN
Platform: UNKNOWN
Requires-Python: >=3.6
Requires-Dist: lmdb
